MANIFEST.in
README.md
setup.py
ultramemcache.py
python_ultramemcached.egg-info/PKG-INFO
python_ultramemcached.egg-info/SOURCES.txt
python_ultramemcached.egg-info/dependency_links.txt
python_ultramemcached.egg-info/requires.txt
python_ultramemcached.egg-info/top_level.txt