Metadata-Version: 1.0
Name: python-ultramemcached
Version: 0.0.3
Summary: A drop in replacement for python-memcached that uses ultramemcache
Home-page: https://github.com/nicholasserra/python-ultramemcached/
Author: Nicholas Serra
Author-email: nick@528hazelwood.com
License: MIT License
Download-URL: https://github.com/nicholasserra/python-ultramemcached/zipball/master
Keywords: python memcache memcached ultramemcached ultramemcache
Platform: UNKNOWN
Classifier: Development Status :: 4 - Beta
Classifier: Intended Audience :: Developers
Classifier: License :: OSI Approved :: MIT License
Classifier: Topic :: Software Development :: Libraries :: Python Modules
Classifier: Topic :: Internet
